Metadata-Version: 2.1
Name: starlette-prometheus-middleware
Version: 0.9.0
Summary: Prometheus integration for Starlette
Home-page: https://github.com/faylixe/starlette-prometheus
License: GPL-3.0+
Keywords: starlette,prometheus,metrics
Author: José Antonio Perdiguero López
Author-email: perdy@perdy.io
Requires-Python: >=3.6,<4.0
Classifier: Development Status :: 5 - Production/Stable
Classifier: Intended Audience :: Developers
Classifier: License :: OSI Approved :: GNU General Public License v3 or later (GPLv3+)
Classifier: Programming Language :: Python :: 3
Classifier: Programming Language :: Python :: 3.6
Classifier: Programming Language :: Python :: 3.7
Classifier: Programming Language :: Python :: 3.8
Classifier: Programming Language :: Python :: 3.9
Classifier: Topic :: Internet :: WWW/HTTP :: HTTP Servers
Classifier: Topic :: Software Development
Classifier: Topic :: Software Development :: Libraries
Requires-Dist: prometheus_client (>=0.9.0,<0.10.0)
Requires-Dist: starlette (>=0.12.2)
Project-URL: Repository, https://github.com/faylixe/starlette-prometheus
